image_url_upload/__init__.py
image_url_upload/apps.py
image_url_upload/views.py
image_url_upload/wagtail_hooks.py
image_url_upload/static/image_url_upload/js/main.js
image_url_upload/templates/image_url_upload/add_via_url.html
wagtail_image_from_url-1.0.2.dist-info/LICENSE
wagtail_image_from_url-1.0.2.dist-info/METADATA
wagtail_image_from_url-1.0.2.dist-info/WHEEL
wagtail_image_from_url-1.0.2.dist-info/top_level.txt
wagtail_image_from_url-1.0.2.dist-info/RECORD
