Metadata-Version: 2.1
Name: wagtail-image-from-url
Version: 1.0.2
Summary: Add images to Wagtail via URL - A production-ready plugin for importing images from external URLs
Author-email: Awais Qureshi <awais.qureshi@arbisoft.com>
License: MIT
Project-URL: Homepage, https://github.com/awais786/wagtail-image-from-url
Project-URL: Bug Tracker, https://github.com/awais786/wagtail-image-from-url/issues
Project-URL: Documentation, https://github.com/awais786/wagtail-image-from-url#readme
Keywords: wagtail,django,cms,image,upload,url,import
Classifier: Development Status :: 4 - Beta
Classifier: Environment :: Web Environment
Classifier: Framework :: Django
Classifier: Framework :: Django :: 4.2
Classifier: Framework :: Django :: 5.0
Classifier: Framework :: Wagtail
Classifier: Framework :: Wagtail :: 5
Classifier: Framework :: Wagtail :: 6
Classifier: Intended Audience :: Developers
Classifier: Operating System :: OS Independent
Classifier: Programming Language :: Python
Classifier: Programming Language :: Python :: 3
Classifier: Programming Language :: Python :: 3.10
Classifier: Programming Language :: Python :: 3.11
Classifier: Programming Language :: Python :: 3.12
Classifier: Programming Language :: Python :: 3.13
Classifier: Topic :: Internet :: WWW/HTTP
Classifier: Topic :: Internet :: WWW/HTTP :: Dynamic Content
Classifier: Topic :: Software Development :: Libraries :: Python Modules
Requires-Python: >=3.10
License-File: LICENSE
Requires-Dist: Django>=4.2
Requires-Dist: Wagtail>=5.0
Requires-Dist: requests>=2.25.0
Requires-Dist: Pillow>=9.0.0
